pdf_bank_statement_parser/__init__.py
pdf_bank_statement_parser/cli.py
pdf_bank_statement_parser/constants.py
pdf_bank_statement_parser/exceptions.py
pdf_bank_statement_parser/export.py
pdf_bank_statement_parser/objects.py
pdf_bank_statement_parser/parse/extract_transactions.py
pdf_bank_statement_parser/parse/output_validation.py
pdf_bank_statement_parser/parse/string_cleaning.py
pdf_bank_statement_parser-0.1.1.dist-info/METADATA
pdf_bank_statement_parser-0.1.1.dist-info/WHEEL
pdf_bank_statement_parser-0.1.1.dist-info/entry_points.txt
pdf_bank_statement_parser-0.1.1.dist-info/licenses/LICENSE
pdf_bank_statement_parser-0.1.1.dist-info/RECORD
