Metadata-Version: 2.3
Name: pdf-bank-statement-parser
Version: 0.1.1
Summary: Command-line tool for converting PDF bank statements into CSV
Project-URL: homepage, https://github.com/J-sephB-lt-n/pdf-bank-statement-parser
Project-URL: changelog, https://github.com/J-sephB-lt-n/pdf-bank-statement-parser/blob/main/CHANGELOG.md
Author-email: Joseph Bolton <joseph.jazz.bolton@gmail.com>
License-File: LICENSE
Classifier: Development Status :: 3 - Alpha
Classifier: Environment :: Console
Classifier: License :: OSI Approved :: GNU General Public License v3 (GPLv3)
Classifier: Natural Language :: English
Classifier: Topic :: File Formats
Classifier: Topic :: Office/Business :: Financial :: Spreadsheet
Classifier: Topic :: Text Processing
Requires-Python: >=3.12
Requires-Dist: pypdfium2>=4.30.0
